pytest-cov.pth
pytest_cov/__init__.py
pytest_cov/compat.py
pytest_cov/embed.py
pytest_cov/engine.py
pytest_cov/plugin.py
pytest_cov-2.12.1.dist-info/AUTHORS.rst
pytest_cov-2.12.1.dist-info/LICENSE
pytest_cov-2.12.1.dist-info/METADATA
pytest_cov-2.12.1.dist-info/WHEEL
pytest_cov-2.12.1.dist-info/entry_points.txt
pytest_cov-2.12.1.dist-info/top_level.txt
pytest_cov-2.12.1.dist-info/RECORD
